pyReturn/__init__.py
pyReturn/response.py
pyReturn-0.0.1.dist-info/METADATA
pyReturn-0.0.1.dist-info/RECORD
pyReturn-0.0.1.dist-info/WHEEL
pyReturn-0.0.1.dist-info/top_level.txt
